FalApp/__init__.py
FalApp/myfunctions.py
tests/__init__.py
tests/test_myfunctions.py
FalApp-0.1.0.dist-info/METADATA
FalApp-0.1.0.dist-info/WHEEL
FalApp-0.1.0.dist-info/top_level.txt
FalApp-0.1.0.dist-info/RECORD
