Metadata-Version: 2.1
Name: FalApp
Version: 0.1.0
Summary: Fareed first Python library
Author: Fareed
